doclib/__init__.py
doclib/admin.py
doclib/apps.py
doclib/models.py
doclib/serializers.py
doclib/tests.py
doclib/urls.py
doclib/views.py
doclib/migrations/0001_initial.py
doclib/migrations/0002_auto_20210314_0452.py
doclib/migrations/__init__.py
doclib/scripts/awsS3.py
doclib/scripts/google_drive_gcs.py
doclib/scripts/__pycache__/awsS3.cpython-36.pyc
doclib/scripts/__pycache__/google_drive_gcs.cpython-36.pyc
doclib/static/img/aws-s3.png
doclib/static/img/gcs.png
doclib/static/js/google_picker.js
doclib/templates/aws_s3.html
doclib/templates/base.html
doclib/templates/errors_page.html
doclib/templates/gcs.html
doclib/templates/local_source.html
doclib/templates/login_digimocker.html
doclib/templates/register_digimocker.html
doclib/templates/showDigimockerFiles.html
doclib/templates/source_display.html
doclib/templates/storage_service.html
doclib/templates/uploadToDm.html
django_doclib-1.2.2.dist-info/LICENSE
django_doclib-1.2.2.dist-info/METADATA
django_doclib-1.2.2.dist-info/WHEEL
django_doclib-1.2.2.dist-info/top_level.txt
django_doclib-1.2.2.dist-info/RECORD
