Metadata-Version: 2.1
Name: django-doclib
Version: 1.2.2
Summary: A Document library
Home-page: https://github.com/Pratyush1606/doclib
License: MIT
Platform: UNKNOWN
Classifier: License :: OSI Approved :: MIT License
Classifier: Programming Language :: Python :: 3.7
Requires-Dist: asgiref (==3.3.1)
Requires-Dist: boto3 (==1.17.42)
Requires-Dist: botocore (==1.20.42)
Requires-Dist: cachetools (==4.2.1)
Requires-Dist: certifi (==2020.12.5)
Requires-Dist: cffi (==1.14.5)
Requires-Dist: chardet (==4.0.0)
Requires-Dist: Django (==3.1.7)
Requires-Dist: djangorestframework (==3.12.4)
Requires-Dist: django-environ (==0.4.5)
Requires-Dist: google-api-core (==1.26.3)
Requires-Dist: google-api-python-client (==2.1.0)
Requires-Dist: google-auth (==1.28.0)
Requires-Dist: google-auth-httplib2 (==0.1.0)
Requires-Dist: google-auth-oauthlib (==0.4.4)
Requires-Dist: google-cloud-core (==1.6.0)
Requires-Dist: google-cloud-storage (==1.37.0)
Requires-Dist: google-crc32c (==1.1.2)
Requires-Dist: google-resumable-media (==1.2.0)
Requires-Dist: googleapis-common-protos (==1.53.0)
Requires-Dist: httplib2 (==0.19.1)
Requires-Dist: idna (==2.10)
Requires-Dist: jmespath (==0.10.0)
Requires-Dist: oauthlib (==3.1.0)
Requires-Dist: packaging (==20.9)
Requires-Dist: protobuf (==3.15.6)
Requires-Dist: pyasn1 (==0.4.8)
Requires-Dist: pyasn1-modules (==0.2.8)
Requires-Dist: pycparser (==2.20)
Requires-Dist: pyparsing (==2.4.7)
Requires-Dist: python-dateutil (==2.8.1)
Requires-Dist: pytz (==2021.1)
Requires-Dist: requests (==2.25.1)
Requires-Dist: requests-oauthlib (==1.3.0)
Requires-Dist: rsa (==4.7.2)
Requires-Dist: s3transfer (==0.3.6)
Requires-Dist: six (==1.15.0)
Requires-Dist: sqlparse (==0.4.1)
Requires-Dist: uritemplate (==3.0.1)
Requires-Dist: urllib3 (==1.26.4)
